aeon/__init__.py
aeonpy-0.0.2.dist-info/METADATA
aeonpy-0.0.2.dist-info/WHEEL
aeonpy-0.0.2.dist-info/top_level.txt
aeonpy-0.0.2.dist-info/RECORD
