Metadata-Version: 2.4
Name: aeonpy
Version: 0.0.2
Summary: Aeon SDK for python
Author: Martin
Requires-Python: >=3.8
Requires-Dist: httpx
Requires-Dist: pydantic
